pyread_swift/__init__.py
pyread_swift/io.py
pyread_swift/peano.py
pyread_swift/read_dataset.py
pyread_swift/read_header.py
pyread_swift/read_healpix.py
pyread_swift/read_lightcone.py
pyread_swift/select_region.py
pyread_swift/split_selection.py
pyread_swift-1.2.0.dist-info/licenses/LICENCE
scripts/cli.py
scripts/combine.py
scripts/grid_snapshots.py
pyread_swift-1.2.0.dist-info/METADATA
pyread_swift-1.2.0.dist-info/WHEEL
pyread_swift-1.2.0.dist-info/entry_points.txt
pyread_swift-1.2.0.dist-info/top_level.txt
pyread_swift-1.2.0.dist-info/RECORD
