Metadata-Version: 2.4
Name: pyread_swift
Version: 1.2.0
Summary: Package to read SWIFT simulation snapshots in MPI.
Author-email: Stuart McAlpine <stuart.mcalpine@fysik.su.se>
License: BSD 3-Clause License
Keywords: swiftsim,simulations,mpi,numerical
Classifier: Programming Language :: Python :: 3
Requires-Python: >=3.9
License-File: LICENCE
Requires-Dist: numpy<2
Requires-Dist: h5py
Requires-Dist: mpi4py
Dynamic: license-file
